mskit/__info__.py
mskit/__init__.py
mskit/bio_databases/__init__.py
mskit/bio_databases/proteome_xchange.py
mskit/bio_databases/pubmed.py
mskit/bio_databases/uniprot.py
mskit/calc/__init__.py
mskit/calc/data_filter.py
mskit/calc/intensity.py
mskit/calc/mass_calc.py
mskit/calc/protein_assignment.py
mskit/calc/quantification.py
mskit/calc/rt.py
mskit/constants/__init__.py
mskit/constants/aa.py
mskit/constants/base.py
mskit/constants/database.py
mskit/constants/enzyme.py
mskit/constants/mass.py
mskit/constants/mod.py
mskit/constants/rt.py
mskit/constants/xler.py
mskit/instrument/__init__.py
mskit/instrument/thermo.py
mskit/metric/__init__.py
mskit/metric/distance.py
mskit/metric/robustness.py
mskit/metric/similarity.py
mskit/ms_analysis_tools/__init__.py
mskit/ms_analysis_tools/comet.py
mskit/ms_analysis_tools/diann.py
mskit/ms_analysis_tools/fragpipe.py
mskit/ms_analysis_tools/go.py
mskit/ms_analysis_tools/mascot.py
mskit/ms_analysis_tools/maxquant.py
mskit/ms_analysis_tools/openswath.py
mskit/ms_analysis_tools/pfind.py
mskit/ms_analysis_tools/philosopher.py
mskit/ms_analysis_tools/plink.py
mskit/ms_analysis_tools/proteome_discoverer.py
mskit/ms_analysis_tools/skyline.py
mskit/ms_analysis_tools/spectronaut.py
mskit/ms_analysis_tools/xwalk.py
mskit/ms_analysis_tools/_diann/__init__.py
mskit/ms_analysis_tools/_diann/diann_constants.py
mskit/ms_analysis_tools/_diann/utils.py
mskit/ms_analysis_tools/_maxquant/__init__.py
mskit/ms_analysis_tools/_maxquant/maxquant_constants.py
mskit/ms_analysis_tools/_maxquant/mq_report_utils.py
mskit/ms_analysis_tools/_maxquant/tsv_to_mq.py
mskit/ms_analysis_tools/_openswath/__init__.py
mskit/ms_analysis_tools/_openswath/openswath_constants.py
mskit/ms_analysis_tools/_openswath/osw_file.py
mskit/ms_analysis_tools/_skyline/__init__.py
mskit/ms_analysis_tools/_skyline/blib.py
mskit/ms_analysis_tools/_skyline/skyline_constants.py
mskit/ms_analysis_tools/_spectronaut/__init__.py
mskit/ms_analysis_tools/_spectronaut/lib_utils.py
mskit-0.6.1.dist-info/LICENSE
mskit-0.6.1.dist-info/METADATA
mskit-0.6.1.dist-info/WHEEL
mskit-0.6.1.dist-info/top_level.txt
mskit-0.6.1.dist-info/RECORD
